tilly_github.py
tilly_github-0.0.1.dist-info/LICENSE
tilly_github-0.0.1.dist-info/METADATA
tilly_github-0.0.1.dist-info/WHEEL
tilly_github-0.0.1.dist-info/entry_points.txt
tilly_github-0.0.1.dist-info/top_level.txt
tilly_github-0.0.1.dist-info/RECORD
